oereb_client/__init__.py
oereb_client/routes.py
oereb_client/static/build/app.css
oereb_client/static/build/app.js
oereb_client/static/build/browser-ponyfill-dLhjz9fn.js
oereb_client/static/build/oereb_client-D4tvOGw1.js
oereb_client/static/i18n/de/locale.json
oereb_client/static/i18n/en/locale.json
oereb_client/static/i18n/fr/locale.json
oereb_client/static/images/logo_oereb_de.jpg
oereb_client/static/images/logo_oereb_fr.jpg
oereb_client/static/images/logo_oereb_it.jpg
oereb_client/static/images/logo_oereb_rm.jpg
oereb_client/static/images/oereb-apple-touch-icon-192x192.png
oereb_client/static/images/oereb-favicon-48x48.png
oereb_client/static/images/oereb-maskable-192x192.png
oereb_client/static/images/oereb-maskable-512x512.png
oereb_client/static/images/oereb-maskable.svg
oereb_client/static/images/oereb-regular-192x192.png
oereb_client/static/images/oereb-regular-512x512.png
oereb_client/static/images/oereb-regular.svg
oereb_client/templates/index.html
oereb_client/templates/manifest.json
oereb_client/views/__init__.py
oereb_client/views/index.py
oereb_client/views/manifest.py
oereb_client/views/search.py
oereb_client-2.4.0.dist-info/licenses/LICENSE
oereb_client-2.4.0.dist-info/METADATA
oereb_client-2.4.0.dist-info/WHEEL
oereb_client-2.4.0.dist-info/entry_points.txt
oereb_client-2.4.0.dist-info/top_level.txt
oereb_client-2.4.0.dist-info/RECORD
