Metadata-Version: 2.4
Name: oereb_client
Version: 2.4.0
Summary: ÖREB Client
Home-page: https://gitlab.com/gf-bl/oereb_client
Author: Karsten Deininger
Author-email: karsten.deininger@bl.ch
Keywords: web pyramid oereb client react openlayers
Classifier: License :: OSI Approved :: BSD License
Classifier: Development Status :: 5 - Production/Stable
Classifier: Programming Language :: Python :: 3.9
Classifier: Programming Language :: Python :: 3.10
Classifier: Programming Language :: Python :: 3.11
Classifier: Programming Language :: Python :: 3.12
Classifier: Framework :: Pyramid
Classifier: Topic :: Internet :: WWW/HTTP
Classifier: Topic :: Internet :: WWW/HTTP :: WSGI :: Application
License-File: LICENSE
Requires-Dist: pyaml-env
Requires-Dist: pyramid
Requires-Dist: pyramid_mako
Requires-Dist: requests-futures
Requires-Dist: waitress
Dynamic: author
Dynamic: author-email
Dynamic: classifier
Dynamic: description
Dynamic: home-page
Dynamic: keywords
Dynamic: license-file
Dynamic: requires-dist
Dynamic: summary
